{
  "project_info": {
    "project_number": "659614678651",
    "project_id": "sisac-b578f",
    "storage_bucket": "sisac-b578f.appspot.com"
  },
  "client": [
    {
      "client_info": {
        "mobilesdk_app_id": "1:659614678651:android:5c19472ad1400aad432cde",
        "android_client_info": {
          "package_name": "com.example.sisac"
        }
      },
      "oauth_client": [
        {
          "client_id": "659614678651-qontp4q3n9kirpervpbc08cpgvmc4ea0.apps.googleusercontent.com",
          "client_type": 3
        }
      ],
      "api_key": [
        {
          "current_key": "AIzaSyDzZrYLb8Ynuzt3KPnIfKcFqx23ry0eFzw"
        }
      ],
      "services": {
        "appinvite_service": {
          "other_platform_oauth_client": [
            {
              "client_id": "659614678651-qontp4q3n9kirpervpbc08cpgvmc4ea0.apps.googleusercontent.com",
              "client_type": 3
            },
            {
              "client_id": "659614678651-7e8mufdh731ue9malq1ok1cae3hdks1d.apps.googleusercontent.com",
              "client_type": 2,
              "ios_info": {
                "bundle_id": "com.sisac.app"
              }
            }
          ]
        }
      }
    }
  ],
  "configuration_version": "1"
}